biosimulators_processes/_VERSION
biosimulators_processes/__init__.py
biosimulators_processes/api/README.md
biosimulators_processes/api/__init__.py
biosimulators_processes/api/build.py
biosimulators_processes/api/compare.py
biosimulators_processes/api/instance.py
biosimulators_processes/api/results.py
biosimulators_processes/api/run.py
biosimulators_processes/api/verify.py
biosimulators_processes/biosimulator_builder.py
biosimulators_processes/containers/__init__.py
biosimulators_processes/containers/exec.py
biosimulators_processes/containers/io.py
biosimulators_processes/data_model/__init__.py
biosimulators_processes/data_model/compare_data_model.py
biosimulators_processes/data_model/sed_data_model.py
biosimulators_processes/data_model/service_data_model.py
biosimulators_processes/data_model/verify_data_model.py
biosimulators_processes/execute.py
biosimulators_processes/experiments/__init__.py
biosimulators_processes/experiments/parameter_optimization.py
biosimulators_processes/experiments/parameter_scan.py
biosimulators_processes/experiments/predict.py
biosimulators_processes/helpers.py
biosimulators_processes/io.py
biosimulators_processes/processes/__init__.py
biosimulators_processes/processes/amici_process.py
biosimulators_processes/processes/cobra_process.py
biosimulators_processes/processes/copasi_process.py
biosimulators_processes/processes/qiskit_process.py
biosimulators_processes/processes/sed_process.py
biosimulators_processes/processes/smoldyn_process.py
biosimulators_processes/processes/tellurium_process.py
biosimulators_processes/processes/utc_process.py
biosimulators_processes/services/__init__.py
biosimulators_processes/services/rest_service.py
biosimulators_processes/simularium_utils.py
biosimulators_processes/steps/__init__.py
biosimulators_processes/steps/bio_compose.py
biosimulators_processes/steps/comparator_step.py
biosimulators_processes/steps/ode_simulation.py
biosimulators_processes/steps/parameter_scan.py
biosimulators_processes/steps/viz.py
biosimulators_processes-0.2.5.dist-info/AUTHORS.md
biosimulators_processes-0.2.5.dist-info/LICENSE
biosimulators_processes-0.2.5.dist-info/METADATA
biosimulators_processes-0.2.5.dist-info/WHEEL
biosimulators_processes-0.2.5.dist-info/RECORD
