Metadata-Version: 2.1
Name: biosimulators-processes
Version: 0.2.5
Summary: Core implementations of process-bigraph.composite.Process aligning with BioSimulators simulator tools.
Author: Alex Patrie
Author-email: alexanderpatrie@gmail.com
Requires-Python: >=3.10
Classifier: Programming Language :: Python :: 3
Classifier: Programming Language :: Python :: 3.10
Classifier: Programming Language :: Python :: 3.11
Classifier: Programming Language :: Python :: 3.12
Provides-Extra: mongo
Provides-Extra: simularium
Provides-Extra: simulators
Requires-Dist: amici (>=0.25.1,<0.26.0) ; extra == "simulators"
Requires-Dist: bigraph-builder (>=0.0.4,<0.0.5)
Requires-Dist: bigraph-schema (>=0.0.38,<0.0.39)
Requires-Dist: bigraph-viz (>=0.0.33,<0.0.34)
Requires-Dist: biosimulators-utils[logging] (>=0.1.188,<0.2.0)
Requires-Dist: cobra (>=0.29.0,<0.30.0)
Requires-Dist: copasi-basico (>=0.69,<0.70) ; extra == "simulators"
Requires-Dist: docker (>=7.1.0,<8.0.0)
Requires-Dist: h5py (>=3.11.0,<4.0.0)
Requires-Dist: jupyterlab (>=4.2.1,<5.0.0)
Requires-Dist: notebook (>=7.2.0,<8.0.0)
Requires-Dist: numpy (>=1.26.4,<2.0.0)
Requires-Dist: process-bigraph (>=0.0.19,<0.0.20)
Requires-Dist: pydantic (>=2.7.2,<3.0.0)
Requires-Dist: pymongo (>=4.8.0,<5.0.0) ; extra == "mongo"
Requires-Dist: python-libsbml (>=5.20.2,<6.0.0)
Requires-Dist: pyyaml (>=6.0.1,<7.0.0)
Requires-Dist: seaborn (>=0.13.2,<0.14.0)
Requires-Dist: simulariumio (>=1.11.0,<2.0.0) ; extra == "simularium"
Requires-Dist: smoldyn[simulariumio] ; extra == "simulators"
Requires-Dist: tellurium (>=2.2.10,<3.0.0) ; extra == "simulators"
Requires-Dist: termcolor (>=2.4.0,<3.0.0)
Requires-Dist: toml (>=0.10.2,<0.11.0)
